MANIFEST.in
README.md
setup.py
alpharotate/__init__.py
alpharotate.egg-info/PKG-INFO
alpharotate.egg-info/SOURCES.txt
alpharotate.egg-info/dependency_links.txt
alpharotate.egg-info/requires.txt
alpharotate.egg-info/top_level.txt
alpharotate/libs/__init__.py
alpharotate/libs/label_name_dict/__init__.py
alpharotate/libs/label_name_dict/label_dict.py
alpharotate/libs/models/__init__.py
alpharotate/libs/models/anchor_heads/__init__.py
alpharotate/libs/models/anchor_heads/anchor_utils.py
alpharotate/libs/models/anchor_heads/generate_anchors.py
alpharotate/libs/models/anchor_heads/generate_h_anchors.py
alpharotate/libs/models/anchor_heads/generate_h_anchors_tf.py
alpharotate/libs/models/anchor_heads/generate_r_anchors.py
alpharotate/libs/models/backbones/__init__.py
alpharotate/libs/models/backbones/build_backbone_p2top6.py
alpharotate/libs/models/backbones/build_backbone_p3top7.py
alpharotate/libs/models/backbones/darknet.py
alpharotate/libs/models/backbones/mobilenet_v2.py
alpharotate/libs/models/backbones/resnet.py
alpharotate/libs/models/backbones/resnet_gluoncv.py
alpharotate/libs/models/backbones/resnet_pytorch.py
alpharotate/libs/models/backbones/efficientnet/__init__.py
alpharotate/libs/models/backbones/efficientnet/demo.py
alpharotate/libs/models/backbones/efficientnet/efficientnet_builder.py
alpharotate/libs/models/backbones/efficientnet/efficientnet_lite_builder.py
alpharotate/libs/models/backbones/efficientnet/efficientnet_model.py
alpharotate/libs/models/backbones/efficientnet/test.py
alpharotate/libs/models/backbones/efficientnet/utils.py
alpharotate/libs/models/backbones/efficientnet/condconv/__init__.py
alpharotate/libs/models/backbones/efficientnet/condconv/condconv_layers.py
alpharotate/libs/models/backbones/efficientnet/condconv/efficientnet_condconv_builder.py
alpharotate/libs/models/backbones/mobilenet/__init__.py
alpharotate/libs/models/backbones/mobilenet/conv_blocks.py
alpharotate/libs/models/backbones/mobilenet/mobilenet.py
alpharotate/libs/models/backbones/mobilenet/mobilenet_v2.py
alpharotate/libs/models/backbones/mobilenet/mobilenet_v2_test.py
alpharotate/libs/models/backbones/slim_nets/__init__.py
