Metadata-Version: 2.1
Name: alpharotate
Version: 1.0.1
Summary: A Rotation Detection Benchmark using TensorFlow
Home-page: https://github.com/yangxue0827/RotationDetection
Author: yangxue0827
Author-email: yangxue-2019-sjtu@sjtu.edu.cn
License: Apache License 2.0
Keywords: AlphaRotate,TensorFlow,Deep Learning,Rotation Detection,Benchmark,SJTU
Platform: UNKNOWN
Classifier: Programming Language :: Python
Classifier: Operating System :: OS Independent
Classifier: Intended Audience :: Developers
Classifier: Intended Audience :: Science/Research
Classifier: Topic :: Scientific/Engineering :: Artificial Intelligence
